returns/__init__.py
returns/_internal/__init__.py
returns/_internal/futures/__init__.py
returns/_internal/futures/_future.py
returns/_internal/futures/_future_result.py
returns/_internal/futures/_reader_future_result.py
returns/_internal/pipeline/__init__.py
returns/_internal/pipeline/flow.py
returns/_internal/pipeline/managed.py
returns/_internal/pipeline/pipe.py
returns/_internal/pipeline/pipe.pyi
returns/context/__init__.py
returns/context/requires_context.py
returns/context/requires_context_future_result.py
returns/context/requires_context_ioresult.py
returns/context/requires_context_result.py
returns/contrib/__init__.py
returns/contrib/hypothesis/__init__.py
returns/contrib/hypothesis/_entrypoint.py
returns/contrib/hypothesis/containers.py
returns/contrib/hypothesis/laws.py
returns/contrib/mypy/__init__.py
returns/contrib/mypy/_consts.py
returns/contrib/mypy/_features/__init__.py
returns/contrib/mypy/_features/curry.py
returns/contrib/mypy/_features/do_notation.py
returns/contrib/mypy/_features/flow.py
returns/contrib/mypy/_features/kind.py
returns/contrib/mypy/_features/partial.py
returns/contrib/mypy/_features/pipe.py
returns/contrib/mypy/_structures/__init__.py
returns/contrib/mypy/_structures/args.py
returns/contrib/mypy/_structures/types.py
returns/contrib/mypy/_typeops/__init__.py
returns/contrib/mypy/_typeops/analtype.py
returns/contrib/mypy/_typeops/fallback.py
returns/contrib/mypy/_typeops/inference.py
returns/contrib/mypy/_typeops/transform_callable.py
returns/contrib/mypy/_typeops/visitor.py
returns/contrib/mypy/returns_plugin.py
returns/contrib/pytest/__init__.py
returns/contrib/pytest/plugin.py
returns/converters.py
returns/curry.py
returns/functions.py
returns/future.py
returns/interfaces/__init__.py
returns/interfaces/altable.py
returns/interfaces/applicative.py
returns/interfaces/bimappable.py
returns/interfaces/bindable.py
returns/interfaces/container.py
returns/interfaces/equable.py
returns/interfaces/failable.py
returns-0.24.0.dist-info/LICENSE
returns-0.24.0.dist-info/METADATA
returns-0.24.0.dist-info/WHEEL
returns-0.24.0.dist-info/entry_points.txt
returns-0.24.0.dist-info/RECORD
