Metadata-Version: 2.1
Name: returns
Version: 0.24.0
Summary: Make your functions return something meaningful, typed, and safe!
Home-page: https://returns.readthedocs.io
License: BSD-3-Clause
Keywords: functional programming,fp,monads,monad,monad transformers,composition,type-safety,mypy,railway-oriented-programming
Author: sobolevn
Author-email: mail@sobolevn.me
Requires-Python: >=3.10,<4.0
Classifier: Development Status :: 4 - Beta
Classifier: Framework :: Hypothesis
Classifier: Intended Audience :: Developers
Classifier: License :: OSI Approved :: BSD License
Classifier: Operating System :: OS Independent
Classifier: Programming Language :: Python :: 3
Classifier: Programming Language :: Python :: 3.10
Classifier: Programming Language :: Python :: 3.11
Classifier: Programming Language :: Python :: 3.12
Classifier: Programming Language :: Python :: 3.13
Classifier: Topic :: Software Development :: Libraries :: Python Modules
Classifier: Topic :: Utilities
Classifier: Typing :: Typed
Provides-Extra: check-laws
Provides-Extra: compatible-mypy
Requires-Dist: hypothesis (>=6.98,<7.0) ; extra == "check-laws"
Requires-Dist: mypy (>=1.12,<1.14) ; extra == "compatible-mypy"
Requires-Dist: pytest (>=8.0,<9.0) ; extra == "check-laws"
Requires-Dist: typing-extensions (>=4.0,<5.0)
Project-URL: Funding, https://github.com/sponsors/dry-python
Project-URL: Repository, https://github.com/dry-python/returns
